
<annotation>
    <folder>Pictures</folder>
    <filename>25.JPG</filename>
    <path>/home/michael/Desktop/DATA/4_Box/Pictures/25.JPG</path>
    <source>
        <database>Unknown</database>
    </source>
    <size>
        <width>410</width>
        <height>410</height>
        <depth>3</depth>
    </size>
    <segmented>0</segmented>
    <object>
        <name>leaf</name>
        <pose>Unspecified</pose>
        <truncated>0</truncated>
        <difficult>0</difficult>
        <bndbox>
            <xmin>156</xmin>
            <ymin>105</ymin>
            <xmax>203</xmax>
            <ymax>165</ymax>
        </bndbox>
    </object>
    <object>
        <name>leaf</name>
        <pose>Unspecified</pose>
        <truncated>0</truncated>
        <difficult>0</difficult>
        <bndbox>
            <xmin>124</xmin>
            <ymin>148</ymin>
            <xmax>155</xmax>
            <ymax>184</ymax>
        </bndbox>
    </object>
    <object>
        <name>leaf</name>
        <pose>Unspecified</pose>
        <truncated>0</truncated>
        <difficult>0</difficult>
        <bndbox>
            <xmin>98</xmin>
            <ymin>194</ymin>
            <xmax>140</xmax>
            <ymax>225</ymax>
        </bndbox>
    </object>
    <object>
        <name>leaf</name>
        <pose>Unspecified</pose>
        <truncated>0</truncated>
        <difficult>0</difficult>
        <bndbox>
            <xmin>128</xmin>
            <ymin>231</ymin>
            <xmax>170</xmax>
            <ymax>290</ymax>
        </bndbox>
    </object>
    <object>
        <name>leaf</name>
        <pose>Unspecified</pose>
        <truncated>0</truncated>
        <difficult>0</difficult>
        <bndbox>
            <xmin>174</xmin>
            <ymin>221</ymin>
            <xmax>220</xmax>
            <ymax>268</ymax>
        </bndbox>
    </object>
    <object>
        <name>leaf</name>
        <pose>Unspecified</pose>
        <truncated>0</truncated>
        <difficult>0</difficult>
        <bndbox>
            <xmin>154</xmin>
            <ymin>183</ymin>
            <xmax>184</xmax>
            <ymax>214</ymax>
        </bndbox>
    </object>
    <object>
        <name>leaf</name>
        <pose>Unspecified</pose>
        <truncated>0</truncated>
        <difficult>0</difficult>
        <bndbox>
            <xmin>171</xmin>
            <ymin>196</ymin>
            <xmax>207</xmax>
            <ymax>221</ymax>
        </bndbox>
    </object>
</annotation>
