
<annotation>
    <folder>Pictures</folder>
    <filename>381.JPG</filename>
    <path>/Volumes/BUZZY/Lab/DATA/4_Box/Pictures/381.JPG</path>
    <source>
        <database>Unknown</database>
    </source>
    <size>
        <width>410</width>
        <height>410</height>
        <depth>3</depth>
    </size>
    <segmented>0</segmented>
    <object>
        <name>leaf</name>
        <pose>Unspecified</pose>
        <truncated>0</truncated>
        <difficult>0</difficult>
        <bndbox>
            <xmin>156</xmin>
            <ymin>136</ymin>
            <xmax>179</xmax>
            <ymax>159</ymax>
        </bndbox>
    </object>
    <object>
        <name>leaf</name>
        <pose>Unspecified</pose>
        <truncated>0</truncated>
        <difficult>0</difficult>
        <bndbox>
            <xmin>180</xmin>
            <ymin>138</ymin>
            <xmax>212</xmax>
            <ymax>173</ymax>
        </bndbox>
    </object>
    <object>
        <name>leaf</name>
        <pose>Unspecified</pose>
        <truncated>0</truncated>
        <difficult>0</difficult>
        <bndbox>
            <xmin>172</xmin>
            <ymin>190</ymin>
            <xmax>203</xmax>
            <ymax>214</ymax>
        </bndbox>
    </object>
    <object>
        <name>leaf</name>
        <pose>Unspecified</pose>
        <truncated>0</truncated>
        <difficult>0</difficult>
        <bndbox>
            <xmin>161</xmin>
            <ymin>161</ymin>
            <xmax>190</xmax>
            <ymax>190</ymax>
        </bndbox>
    </object>
</annotation>
